snr_package/__init__.py
snr_package/snr_calc.py
tests/__init__.py
tests/test_snr_calc.py
snr_calc-0.1.1.dist-info/LICENSE
snr_calc-0.1.1.dist-info/METADATA
snr_calc-0.1.1.dist-info/WHEEL
snr_calc-0.1.1.dist-info/top_level.txt
snr_calc-0.1.1.dist-info/RECORD
