Metadata-Version: 2.1
Name: snr-calc
Version: 0.1.1
Summary: A package to calculate SNR from audio files
Home-page: UNKNOWN
Author: Anthony Soronnadi
Author-email: anthony12soronnadi@gmail.com
License: UNKNOWN
Platform: UNKNOWN
Classifier: Programming Language :: Python :: 3
Classifier: License :: OSI Approved :: MIT License
Classifier: Operating System :: OS Independent
Requires-Python: >=3.10
License-File: LICENSE
Requires-Dist: librosa
Requires-Dist: numpy
